deltachat2/__init__.py
deltachat2/_utils.py
deltachat2/bot.py
deltachat2/client.py
deltachat2/events.py
deltachat2/rpc.py
deltachat2/transport.py
deltachat2/types.py
deltachat2/util.py
deltachat2-0.9.0.dist-info/licenses/LICENSE
deltachat2-0.9.0.dist-info/METADATA
deltachat2-0.9.0.dist-info/WHEEL
deltachat2-0.9.0.dist-info/top_level.txt
deltachat2-0.9.0.dist-info/RECORD
