Metadata-Version: 2.4
Name: deltachat2
Version: 0.9.0
Summary: Client library for Delta Chat core JSON-RPC interface
Author-email: adbenitez <adb@merlinux.eu>
Project-URL: Homepage, https://github.com/adbenitez/deltachat2
Keywords: deltachat
Classifier: Development Status :: 4 - Beta
Classifier: Programming Language :: Python :: 3
Classifier: Intended Audience :: Developers
Classifier: License :: OSI Approved :: Mozilla Public License 2.0 (MPL 2.0)
Requires-Python: >=3.10
License-File: LICENSE
Provides-Extra: full
Requires-Dist: deltachat-rpc-server>=2.35.0; extra == "full"
Provides-Extra: dev
Requires-Dist: deltachat-rpc-server; extra == "dev"
Requires-Dist: black; extra == "dev"
Requires-Dist: mypy; extra == "dev"
Requires-Dist: isort; extra == "dev"
Requires-Dist: pylint; extra == "dev"
Requires-Dist: pylama; extra == "dev"
Requires-Dist: pytest; extra == "dev"
Dynamic: license-file
